ogameasure/__init__.py
ogameasure/communicator/__init__.py
ogameasure/communicator/communicator.py
ogameasure/communicator/ethernet.py
ogameasure/communicator/gpib_prologix.py
ogameasure/communicator/serial.py
ogameasure/communicator/usb.py
ogameasure/device/Agilent/E4418.py
ogameasure/device/Agilent/E8247.py
ogameasure/device/Agilent/E8257.py
ogameasure/device/Agilent/N9342.py
ogameasure/device/Agilent/N9938.py
ogameasure/device/Agilent/__init__.py
ogameasure/device/Agilent/agilent_11713.py
ogameasure/device/Anritsu/__init__.py
ogameasure/device/Anritsu/ma24126a.py
ogameasure/device/Anritsu/mg3692c.py
ogameasure/device/Anritsu/ml2437a.py
ogameasure/device/Canon/M100_raspi.py
ogameasure/device/Canon/__init__.py
ogameasure/device/Cosmotechs/__init__.py
ogameasure/device/Cosmotechs/sp100.py
ogameasure/device/ELVA1/GPDVC15.py
ogameasure/device/ELVA1/__init__.py
ogameasure/device/HEIDENHAIN/ND287.py
ogameasure/device/HEIDENHAIN/__init__.py
ogameasure/device/KIKUSUI/PMX18.py
ogameasure/device/KIKUSUI/__init__.py
ogameasure/device/Lakeshore/__init__.py
ogameasure/device/Lakeshore/model218.py
ogameasure/device/Lakeshore/model218_usb.py
ogameasure/device/Lakeshore/model331.py
ogameasure/device/Pfeiffer/__init__.py
ogameasure/device/Pfeiffer/tpg261.py
ogameasure/device/Pfeiffer/tpg261_lan.py
ogameasure/device/Phasematrix/QuickSyn_FSW0000.py
ogameasure/device/Phasematrix/__init__.py
ogameasure/device/SCPI/__init__.py
ogameasure/device/SCPI/scpi.py
ogameasure/device/SENA/__init__.py
ogameasure/device/SENA/adios.py
ogameasure/device/TandD/__init__.py
ogameasure/device/TandD/tr_73u.py
ogameasure/device/__init__.py
ogameasure/device/device.py
ogameasure/interface/__init__.py
ogameasure-0.6.1.dist-info/METADATA
ogameasure-0.6.1.dist-info/WHEEL
ogameasure-0.6.1.dist-info/RECORD
