Metadata-Version: 2.1
Name: ogameasure
Version: 0.6.1
Summary: Driver for SCPI device
Home-page: https://github.com/ogawa-ros/ogameasure
License: MIT
Author: Shota Ueda
Author-email: s7u27astr0@gmail.com>,Tatsumi Ishikawa <t.ishikawa@a.phys.nagoya-u.ac.jp
Maintainer: Rin Yamada
Maintainer-email: yamada@a.phys.nagoya-u.ac.jp
Requires-Python: >=3.8,<4.0
Classifier: License :: OSI Approved :: MIT License
Classifier: Programming Language :: Python :: 3
Classifier: Programming Language :: Python :: 3.8
Classifier: Programming Language :: Python :: 3.9
Classifier: Programming Language :: Python :: 3.10
Classifier: Programming Language :: Python :: 3.11
Classifier: Programming Language :: Python :: 3.12
Requires-Dist: numpy (>=1.21.2,<2.0.0)
Requires-Dist: pyserial (>=3.5,<4.0)
